training_plugins/__init__.py
training_plugins/plugins/__init__.py
training_plugins/plugins/validation_plugin.py
training_plugins_ChrisPrein-1.0.0rc1.dist-info/LICENSE
training_plugins_ChrisPrein-1.0.0rc1.dist-info/METADATA
training_plugins_ChrisPrein-1.0.0rc1.dist-info/WHEEL
training_plugins_ChrisPrein-1.0.0rc1.dist-info/top_level.txt
training_plugins_ChrisPrein-1.0.0rc1.dist-info/RECORD
