Metadata-Version: 2.1
Name: training-plugins-ChrisPrein
Version: 1.0.0rc1
Summary: A package containing custom operators.
Home-page: https://github.com/ChrisPrein/training-plugins
Author: ChrisPrein
Author-email: e01529038@student.tuwien.ac.at
Project-URL: Bug Tracker, https://github.com/ChrisPrein/training-plugins/issues
Classifier: Programming Language :: Python :: 3
Classifier: License :: OSI Approved :: MIT License
Classifier: Operating System :: OS Independent
Requires-Python: >=3.6
License-File: LICENSE
